reportportal_behave/__init__.py
reportportal_behave/behave_integration_service.py
reportportal_behave/reportportal_service.py
reportportal_behave/entities/__init__.py
reportportal_behave/entities/feature.py
reportportal_behave/entities/scenario.py
reportportal_behave/entities/step.py
reportportal_behave_client-1.1.1.dist-info/LICENSE
reportportal_behave_client-1.1.1.dist-info/METADATA
reportportal_behave_client-1.1.1.dist-info/WHEEL
reportportal_behave_client-1.1.1.dist-info/top_level.txt
reportportal_behave_client-1.1.1.dist-info/RECORD
