Metadata-Version: 2.1
Name: reportportal-behave-client
Version: 1.1.1
Summary: ReportPortal integration client lib
Home-page: https://github.com/Adrian-Tamas/reportportal-behave-integration-client-lib
Author: Adrian Tamas
Author-email: adi.tamas@outlook.com
License: MIT
Platform: UNKNOWN
Classifier: Programming Language :: Python :: 3
Classifier: License :: OSI Approved :: MIT License
Classifier: Operating System :: OS Independent
Requires-Python: >=3
Requires-Dist: mss (==5.1.0)
Requires-Dist: behave (==1.2.6)
Requires-Dist: reportportal-client (==5.0.3)
